dbdump/__init__.py
dbdump/mysqldbToExcel.py
dbdump-0.0.7.dist-info/LICENCE.txt
dbdump-0.0.7.dist-info/METADATA
dbdump-0.0.7.dist-info/WHEEL
dbdump-0.0.7.dist-info/top_level.txt
dbdump-0.0.7.dist-info/RECORD
